{"r":"NitroSurge","college":"Vishnu institute of technology","name":["Giri prakash Annam","Venkatesh.Bandi","M.Durga Prasad","Manikanta.J.V","Abdul.azeem"],"year":["3rd year","3rd year","3rd year","3rd year","3rd year"],"branch":["Mechanical","Mechanical","Mechanical","Mechanical","Mechanical"],"email":["giriprakash135@gmail.com","venkateshbandi1996@gmail.com","giriprakash135@gmail.com","manikantajakkamsetti99@gmail.com","giriprakash135@gmail.com"],"phone":["9010724583","7036376089","8897752787","9666431946","9492889192"],"extra":""}